flappy_bird_env/__init__.py
flappy_bird_env/__main__.py
flappy_bird_env/background.py
flappy_bird_env/base.py
flappy_bird_env/bird.py
flappy_bird_env/drawable.py
flappy_bird_env/flappy_bird_env.py
flappy_bird_env/movable.py
flappy_bird_env/pipe.py
flappy_bird_env/images/__init__.py
flappy_bird_env/images/background.png
flappy_bird_env/images/base.png
flappy_bird_env/images/downflap.png
flappy_bird_env/images/midflap.png
flappy_bird_env/images/pipe.png
flappy_bird_env/images/upflap.png
flappy_bird_env-0.1.6.dist-info/LICENSE
flappy_bird_env-0.1.6.dist-info/METADATA
flappy_bird_env-0.1.6.dist-info/WHEEL
flappy_bird_env-0.1.6.dist-info/top_level.txt
flappy_bird_env-0.1.6.dist-info/RECORD
