Metadata-Version: 2.1
Name: flappy-bird-env
Version: 0.1.6
Summary: Flappy Bird as a Farama Gymnasium environment.
Author-email: Roberto Schiavone <hello@robertoschiavone.io>
Maintainer-email: Roberto Schiavone <hello@robertoschiavone.io>
License: MIT License
Project-URL: homepage, https://github.com/robertoschiavone/flappy-bird-env
Project-URL: documentation, https://github.com/robertoschiavone/flappy-bird-env
Project-URL: repository, https://github.com/robertoschiavone/flappy-bird-env.git
Project-URL: changelog, https://github.com/robertoschiavone/flappy-bird-env/releases
Keywords: flappy-bird,gymnasium,reinforcement-learning
Classifier: License :: OSI Approved :: MIT License
Classifier: Programming Language :: Python :: 3
Classifier: Topic :: Software Development :: Libraries
Requires-Python: >=3.11
License-File: LICENSE
Requires-Dist: gymnasium (~=0.29.0)
Requires-Dist: numpy (~=1.25.2)
Requires-Dist: pygame (~=2.5.0)
